memspectrum/GenerateTimeSeries.py
memspectrum/__init__.py
memspectrum/memspectrum.py
memspectrum-1.3.0.dist-info/LICENSE
memspectrum-1.3.0.dist-info/METADATA
memspectrum-1.3.0.dist-info/WHEEL
memspectrum-1.3.0.dist-info/top_level.txt
memspectrum-1.3.0.dist-info/RECORD
