Metadata-Version: 2.1
Name: memspectrum
Version: 1.3.0
Summary: maximum entropy spectral analysis
Home-page: https://github.com/martini-alessandro/Maximum-Entropy-Spectrum/
Author: Alessandro Martini
Author-email: martini.alessandr@gmail.com
License: CC by 4.0
License-File: LICENSE
Requires-Dist: numpy
Requires-Dist: scipy
